manip/__init__.py
manip-0.2.dist-info/LICENSE
manip-0.2.dist-info/METADATA
manip-0.2.dist-info/WHEEL
manip-0.2.dist-info/top_level.txt
manip-0.2.dist-info/RECORD
