Metadata-Version: 2.1
Name: manip
Version: 0.2
Summary: A manipulation package to change whole folders.
Home-page: https://github.com/Flipecs/file_manip.git
Author: Felipe Amaral
Author-email: costinha.fca@gmail.com
License: UNKNOWN
Platform: UNKNOWN
Classifier: Programming Language :: Python :: 3
Classifier: License :: OSI Approved :: MIT License
Classifier: Operating System :: OS Independent
